2_Splited_IO/2_1_Phase_Acc/chiptest/logs/phase_accumulator.v
//      // verilator_coverage annotation
        module phase_accumulator (
 004327 	input 			clk,
 000041 	input			En,
%000003 	input 	[19:0] 	FCW,
 000630 	output 			Vld,
 000291 	output 	reg [1:0]	Aout,
 000044 	output 	reg		ISout
        );
        	// Rdy_source (enable ring counter) ---------------
        	integer i;
 000630     reg     [6:0]   RdyCtl;
 002164 	always @(posedge clk) begin
 002142 		if(!En) RdyCtl <= 7'b0100000;
 002142 		else begin //activate
 002142 			RdyCtl[0] <= RdyCtl[6];
 012852 			for (i=0; i<6; i=i+1)
 012852 				RdyCtl[i+1] <= RdyCtl[i];
        		end	
        	end 
        	assign Vld = RdyCtl[6];
        	
        	// Accumulator & Quadrant Modification ------------
 000044 	reg [19:0] acc_reg;
 000029 	reg [11:0] Atmp;
        	
 002164 	always @(posedge clk) begin
 002142 		if (!En) begin
 000022 			acc_reg <= 20'd0;
 000022 			Atmp <= 12'd0;
        		end
 002142 		else begin
 001827 			if (RdyCtl[6]) begin
        				// Accumulator 
 000315 				acc_reg <= acc_reg + FCW; 
        				
        				// Quadrant Modification
 000026 				if 		(acc_reg[19:18] == 2'b01) 
 000026 					Atmp <= {2'b11, acc_reg[17:8]}; // 2->4 plane
 000270 				else if (acc_reg[19:18] == 2'b10) 
 000019 					Atmp <= {2'b00, acc_reg[17:8]}; // 3->1 plane
        				else 
 000270 					Atmp <= acc_reg[19:8];
        			end
        		end
        	end
        	
        	//Invert Sign ------------------------------------
 002164 	always @(posedge clk) begin
 001848 		if (RdyCtl[5]) begin
 000271 			if (acc_reg[19]^acc_reg[18]) ISout <= 1;
 000271 			else ISout <= 0;
        		end
        	end
        
        	// Xin & Xout ------------------------------------
 002165 	always @* begin
 000315 		if		(RdyCtl[0])		Aout = Atmp[1:0];
 000315 		else if (RdyCtl[1]) 	Aout = Atmp[3:2];
 000315 		else if (RdyCtl[2]) 	Aout = Atmp[5:4];
 000294 		else if (RdyCtl[3]) 	Aout = Atmp[7:6];
 000294 		else if (RdyCtl[4]) 	Aout = Atmp[9:8];
 000316 		else if (RdyCtl[5]) 	Aout = Atmp[11:10];
 000316 		else 					Aout = 2'bxx;
        	end
        	
        endmodule

2_Splited_IO/2_1_Phase_Acc/source/tb_phase_accumulator.v
module tb_phase_accumulator();
	reg clk;
	reg En;
	reg [19:0]FCW;
	wire Vld;
	wire [1:0] Aout;
	wire ISout;
	
	phase_accumulator dut(
		.clk(clk),
		.En(En),
		.FCW(FCW),
		.Vld(Vld),
		.Aout(Aout),
		.ISout(ISout)
	);
	
	always #10 clk = ~clk;
	
	initial begin
		$dumpfile("pa_test.vcd"); 
		$dumpvars(0, dut);
		
		clk <= 0;
		FCW <= 0;//5
		//deactivate
		En <= 0;
		repeat (2) @(posedge clk);
		
		//activate
		#10
		FCW <= 20'h80000;
		En <= 1;
		repeat (5) @(posedge clk);
		
		#10
		repeat (5) @(posedge clk);
		
		repeat (1000) @(posedge clk);
		$finish;
	end
	
endmodule

2_Splited_IO/2_1_Phase_Acc/source/pa_test.vcd
$date
	Tue Feb 25 18:16:06 2025
$end
$version
	Icarus Verilog
$end
$timescale
	1s
$end
$scope module tb_phase_accumulator $end
$scope module dut $end
$var wire 1 ! En $end
$var wire 20 " FCW [19:0] $end
$var wire 1 # clk $end
$var wire 1 $ Vld $end
$var reg 2 % Aout [1:0] $end
$var reg 12 & Atmp [11:0] $end
$var reg 1 ' ISout $end
$var reg 7 ( RdyCtl [6:0] $end
$var reg 20 ) acc_reg [19:0] $end
$var integer 32 * i [31:0] $end
$upscope $end
$upscope $end
$enddefinitions $end
$comment Show the parameter values. $end
$dumpall
$end
#0
$dumpvars
bx *
bx )
bx (
x'
b0 &
bx %
x$
0#
b0 "
0!
$end
#10
b0 %
0$
b1 (
b0 )
1#
#20
0#
#30
1#
#40
1!
b1000000000000 "
0#
#50
b10 (
b110 *
1#
#60
0#
#70
b100 (
b110 *
1#
#80
0#
#90
b1000 (
b110 *
1#
#100
0#
#110
b10000 (
b110 *
1#
#120
0#
#130
b100000 (
b110 *
1#
#140
0#
#150
bx %
0'
1$
b1000000 (
b110 *
1#
#160
0#
#170
b0 %
0$
b1 (
b1000000000000 )
b110 *
1#
#180
0#
#190
b10 (
b110 *
1#
#200
0#
#210
b100 (
b110 *
1#
#220
0#
#230
b1000 (
b110 *
1#
#240
0#
#250
b10000 (
b110 *
1#
#260
0#
#270
b100000 (
b110 *
1#
#280
0#
#290
bx %
b10000 &
1$
b1000000 (
b110 *
1#
#300
0#
#310
b0 %
0$
b10000000000000 )
b1 (
b110 *
1#
#320
0#
#330
b10 (
b110 *
1#
#340
0#
#350
b1 %
b100 (
b110 *
1#
#360
0#
#370
b0 %
b1000 (
b110 *
1#
#380
0#
#390
b10000 (
b110 *
1#
#400
0#
#410
b100000 (
b110 *
1#
#420
0#
#430
bx %
b100000 &
1$
b1000000 (
b110 *
1#
#440
0#
#450
b0 %
0$
b1 (
b11000000000000 )
b110 *
1#
#460
0#
#470
b10 (
b110 *
1#
#480
0#
#490
b10 %
b100 (
b110 *
1#
#500
0#
#510
b0 %
b1000 (
b110 *
1#
#520
0#
#530
b10000 (
b110 *
1#
#540
0#
#550
b100000 (
b110 *
1#
#560
0#
#570
bx %
b110000 &
1$
b1000000 (
b110 *
1#
#580
0#
#590
b0 %
0$
b100000000000000 )
b1 (
b110 *
1#
#600
0#
#610
b10 (
b110 *
1#
#620
0#
#630
b11 %
b100 (
b110 *
1#
#640
0#
#650
b0 %
b1000 (
b110 *
1#
#660
0#
#670
b10000 (
b110 *
1#
#680
0#
#690
b100000 (
b110 *
1#
#700
0#
#710
bx %
b1000000 &
1$
b1000000 (
b110 *
1#
#720
0#
#730
b0 %
0$
b1 (
b101000000000000 )
b110 *
1#
#740
0#
#750
b10 (
b110 *
1#
#760
0#
#770
b100 (
b110 *
1#
#780
0#
#790
b1 %
b1000 (
b110 *
1#
#800
0#
#810
b0 %
b10000 (
b110 *
1#
#820
0#
#830
b100000 (
b110 *
1#
#840
0#
#850
bx %
b1010000 &
1$
b1000000 (
b110 *
1#
#860
0#
#870
b0 %
0$
b110000000000000 )
b1 (
b110 *
1#
#880
0#
#890
b10 (
b110 *
1#
#900
0#
#910
b1 %
b100 (
b110 *
1#
#920
0#
#930
b1000 (
b110 *
1#
#940
0#
#950
b0 %
b10000 (
b110 *
1#
#960
0#
#970
b100000 (
b110 *
1#
#980
0#
#990
bx %
b1100000 &
1$
b1000000 (
b110 *
1#
#1000
0#
#1010
b0 %
0$
b1 (
b111000000000000 )
b110 *
1#
#1020
0#
#1030
b10 (
b110 *
1#
#1040
0#
#1050
b10 %
b100 (
b110 *
1#
#1060
0#
#1070
b1 %
b1000 (
b110 *
1#
#1080
0#
#1090
b0 %
b10000 (
b110 *
1#
#1100
0#
#1110
b100000 (
b110 *
1#
#1120
0#
#1130
bx %
b1110000 &
1$
b1000000 (
b110 *
1#
#1140
0#
#1150
b0 %
0$
b1000000000000000 )
b1 (
b110 *
1#
#1160
0#
#1170
b10 (
b110 *
1#
#1180
0#
#1190
b11 %
b100 (
b110 *
1#
#1200
0#
#1210
b1 %
b1000 (
b110 *
1#
#1220
0#
#1230
b0 %
b10000 (
b110 *
1#
#1240
0#
#1250
b100000 (
b110 *
1#
#1260
0#
#1270
bx %
b10000000 &
1$
b1000000 (
b110 *
1#
#1280
0#
#1290
b0 %
0$
b1 (
b1001000000000000 )
b110 *
1#
#1300
0#
#1310
b10 (
b110 *
1#
#1320
0#
#1330
b100 (
b110 *
1#
#1340
0#
#1350
b10 %
b1000 (
b110 *
1#
#1360
0#
#1370
b0 %
b10000 (
b110 *
1#
#1380
0#
#1390
b100000 (
b110 *
1#
#1400
0#
#1410
bx %
b10010000 &
1$
b1000000 (
b110 *
1#
#1420
0#
#1430
b0 %
0$
b1010000000000000 )
b1 (
b110 *
1#
#1440
0#
#1450
b10 (
b110 *
1#
#1460
0#
#1470
b1 %
b100 (
b110 *
1#
#1480
0#
#1490
b10 %
b1000 (
b110 *
1#
#1500
0#
#1510
b0 %
b10000 (
b110 *
1#
#1520
0#
#1530
b100000 (
b110 *
1#
#1540
0#
#1550
bx %
b10100000 &
1$
b1000000 (
b110 *
1#
#1560
0#
#1570
b0 %
0$
b1 (
b1011000000000000 )
b110 *
1#
#1580
0#
#1590
b10 (
b110 *
1#
#1600
0#
#1610
b10 %
b100 (
b110 *
1#
#1620
0#
#1630
b1000 (
b110 *
1#
#1640
0#
#1650
b0 %
b10000 (
b110 *
1#
#1660
0#
#1670
b100000 (
b110 *
1#
#1680
0#
#1690
bx %
b10110000 &
1$
b1000000 (
b110 *
1#
#1700
0#
#1710
b0 %
0$
b1100000000000000 )
b1 (
b110 *
1#
#1720
0#
#1730
b10 (
b110 *
1#
#1740
0#
#1750
b11 %
b100 (
b110 *
1#
#1760
0#
#1770
b10 %
b1000 (
b110 *
1#
#1780
0#
#1790
b0 %
b10000 (
b110 *
1#
#1800
0#
#1810
b100000 (
b110 *
1#
#1820
0#
#1830
bx %
b11000000 &
1$
b1000000 (
b110 *
1#
#1840
0#
#1850
b0 %
0$
b1 (
b1101000000000000 )
b110 *
1#
#1860
0#
#1870
b10 (
b110 *
1#
#1880
0#
#1890
b100 (
b110 *
1#
#1900
0#
#1910
b11 %
b1000 (
b110 *
1#
#1920
0#
#1930
b0 %
b10000 (
b110 *
1#
#1940
0#
#1950
b100000 (
b110 *
1#
#1960
0#
#1970
bx %
b11010000 &
1$
b1000000 (
b110 *
1#
#1980
0#
#1990
b0 %
0$
b1110000000000000 )
b1 (
b110 *
1#
#2000
0#
#2010
b10 (
b110 *
1#
#2020
0#
#2030
b1 %
b100 (
b110 *
1#
#2040
0#
#2050
b11 %
b1000 (
b110 *
1#
#2060
0#
#2070
b0 %
b10000 (
b110 *
1#
#2080
0#
#2090
b100000 (
b110 *
1#
#2100
0#
#2110
bx %
b11100000 &
1$
b1000000 (
b110 *
1#
#2120
0#
#2130
b0 %
0$
b1 (
b1111000000000000 )
b110 *
1#
#2140
0#
#2150
b10 (
b110 *
1#
#2160
0#
#2170
b10 %
b100 (
b110 *
1#
#2180
0#
#2190
b11 %
b1000 (
b110 *
1#
#2200
0#
#2210
b0 %
b10000 (
b110 *
1#
#2220
0#
#2230
b100000 (
b110 *
1#
#2240
0#
#2250
bx %
b11110000 &
1$
b1000000 (
b110 *
1#
#2260
0#
#2270
b0 %
0$
b10000000000000000 )
b1 (
b110 *
1#
#2280
0#
#2290
b10 (
b110 *
1#
#2300
0#
#2310
b11 %
b100 (
b110 *
1#
#2320
0#
#2330
b1000 (
b110 *
1#
#2340
0#
#2350
b0 %
b10000 (
b110 *
1#
#2360
0#
#2370
b100000 (
b110 *
1#
#2380
0#
#2390
bx %
b100000000 &
1$
b1000000 (
b110 *
1#
#2400
0#
#2410
b0 %
0$
b1 (
b10001000000000000 )
b110 *
1#
#2420
0#
#2430
b10 (
b110 *
1#
#2440
0#
#2450
b100 (
b110 *
1#
#2460
0#
#2470
b1000 (
b110 *
1#
#2480
0#
#2490
b1 %
b10000 (
b110 *
1#
#2500
0#
#2510
b0 %
b100000 (
b110 *
1#
#2520
0#
#2530
bx %
b100010000 &
1$
b1000000 (
b110 *
1#
#2540
0#
#2550
b0 %
0$
b10010000000000000 )
b1 (
b110 *
1#
#2560
0#
#2570
b10 (
b110 *
1#
#2580
0#
#2590
b1 %
b100 (
b110 *
1#
#2600
0#
#2610
b0 %
b1000 (
b110 *
1#
#2620
0#
#2630
b1 %
b10000 (
b110 *
1#
#2640
0#
#2650
b0 %
b100000 (
b110 *
1#
#2660
0#
#2670
bx %
b100100000 &
1$
b1000000 (
b110 *
1#
#2680
0#
#2690
b0 %
0$
b1 (
b10011000000000000 )
b110 *
1#
#2700
0#
#2710
b10 (
b110 *
1#
#2720
0#
#2730
b10 %
b100 (
b110 *
1#
#2740
0#
#2750
b0 %
b1000 (
b110 *
1#
#2760
0#
#2770
b1 %
b10000 (
b110 *
1#
#2780
0#
#2790
b0 %
b100000 (
b110 *
1#
#2800
0#
#2810
bx %
b100110000 &
1$
b1000000 (
b110 *
1#
#2820
0#
#2830
b0 %
0$
b10100000000000000 )
b1 (
b110 *
1#
#2840
0#
#2850
b10 (
b110 *
1#
#2860
0#
#2870
b11 %
b100 (
b110 *
1#
#2880
0#
#2890
b0 %
b1000 (
b110 *
1#
#2900
0#
#2910
b1 %
b10000 (
b110 *
1#
#2920
0#
#2930
b0 %
b100000 (
b110 *
1#
#2940
0#
#2950
bx %
b101000000 &
1$
b1000000 (
b110 *
1#
#2960
0#
#2970
b0 %
0$
b1 (
b10101000000000000 )
b110 *
1#
#2980
0#
#2990
b10 (
b110 *
1#
#3000
0#
#3010
b100 (
b110 *
1#
#3020
0#
#3030
b1 %
b1000 (
b110 *
1#
#3040
0#
#3050
b10000 (
b110 *
1#
#3060
0#
#3070
b0 %
b100000 (
b110 *
1#
#3080
0#
#3090
bx %
b101010000 &
1$
b1000000 (
b110 *
1#
#3100
0#
#3110
b0 %
0$
b10110000000000000 )
b1 (
b110 *
1#
#3120
0#
#3130
b10 (
b110 *
1#
#3140
0#
#3150
b1 %
b100 (
b110 *
1#
#3160
0#
#3170
b1000 (
b110 *
1#
#3180
0#
#3190
b10000 (
b110 *
1#
#3200
0#
#3210
b0 %
b100000 (
b110 *
1#
#3220
0#
#3230
bx %
b101100000 &
1$
b1000000 (
b110 *
1#
#3240
0#
#3250
b0 %
0$
b1 (
b10111000000000000 )
b110 *
1#
#3260
0#
#3270
b10 (
b110 *
1#
#3280
0#
#3290
b10 %
b100 (
b110 *
1#
#3300
0#
#3310
b1 %
b1000 (
b110 *
1#
#3320
0#
#3330
b10000 (
b110 *
1#
#3340
0#
#3350
b0 %
b100000 (
b110 *
1#
#3360
0#
#3370
bx %
b101110000 &
1$
b1000000 (
b110 *
1#
#3380
0#
#3390
b0 %
0$
b11000000000000000 )
b1 (
b110 *
1#
#3400
0#
#3410
b10 (
b110 *
1#
#3420
0#
#3430
b11 %
b100 (
b110 *
1#
#3440
0#
#3450
b1 %
b1000 (
b110 *
1#
#3460
0#
#3470
b10000 (
b110 *
1#
#3480
0#
#3490
b0 %
b100000 (
b110 *
1#
#3500
0#
#3510
bx %
b110000000 &
1$
b1000000 (
b110 *
1#
#3520
0#
#3530
b0 %
0$
b1 (
b11001000000000000 )
b110 *
1#
#3540
0#
#3550
b10 (
b110 *
1#
#3560
0#
#3570
b100 (
b110 *
1#
#3580
0#
#3590
b10 %
b1000 (
b110 *
1#
#3600
0#
#3610
b1 %
b10000 (
b110 *
1#
#3620
0#
#3630
b0 %
b100000 (
b110 *
1#
#3640
0#
#3650
bx %
b110010000 &
1$
b1000000 (
b110 *
1#
#3660
0#
#3670
b0 %
0$
b11010000000000000 )
b1 (
b110 *
1#
#3680
0#
#3690
b10 (
b110 *
1#
#3700
0#
#3710
b1 %
b100 (
b110 *
1#
#3720
0#
#3730
b10 %
b1000 (
b110 *
1#
#3740
0#
#3750
b1 %
b10000 (
b110 *
1#
#3760
0#
#3770
b0 %
b100000 (
b110 *
1#
#3780
0#
#3790
bx %
b110100000 &
1$
b1000000 (
b110 *
1#
#3800
0#
#3810
b0 %
0$
b1 (
b11011000000000000 )
b110 *
1#
#3820
0#
#3830
b10 (
b110 *
1#
#3840
0#
#3850
b10 %
b100 (
b110 *
1#
#3860
0#
#3870
b1000 (
b110 *
1#
#3880
0#
#3890
b1 %
b10000 (
b110 *
1#
#3900
0#
#3910
b0 %
b100000 (
b110 *
1#
#3920
0#
#3930
bx %
b110110000 &
1$
b1000000 (
b110 *
1#
#3940
0#
#3950
b0 %
0$
b11100000000000000 )
b1 (
b110 *
1#
#3960
0#
#3970
b10 (
b110 *
1#
#3980
0#
#3990
b11 %
b100 (
b110 *
1#
#4000
0#
#4010
b10 %
b1000 (
b110 *
1#
#4020
0#
#4030
b1 %
b10000 (
b110 *
1#
#4040
0#
#4050
b0 %
b100000 (
b110 *
1#
#4060
0#
#4070
bx %
b111000000 &
1$
b1000000 (
b110 *
1#
#4080
0#
#4090
b0 %
0$
b1 (
b11101000000000000 )
b110 *
1#
#4100
0#
#4110
b10 (
b110 *
1#
#4120
0#
#4130
b100 (
b110 *
1#
#4140
0#
#4150
b11 %
b1000 (
b110 *
1#
#4160
0#
#4170
b1 %
b10000 (
b110 *
1#
#4180
0#
#4190
b0 %
b100000 (
b110 *
1#
#4200
0#
#4210
bx %
b111010000 &
1$
b1000000 (
b110 *
1#
#4220
0#
#4230
b0 %
0$
b11110000000000000 )
b1 (
b110 *
1#
#4240
0#
#4250
b10 (
b110 *
1#
#4260
0#
#4270
b1 %
b100 (
b110 *
1#
#4280
0#
#4290
b11 %
b1000 (
b110 *
1#
#4300
0#
#4310
b1 %
b10000 (
b110 *
1#
#4320
0#
#4330
b0 %
b100000 (
b110 *
1#
#4340
0#
#4350
bx %
b111100000 &
1$
b1000000 (
b110 *
1#
#4360
0#
#4370
b0 %
0$
b1 (
b11111000000000000 )
b110 *
1#
#4380
0#
#4390
b10 (
b110 *
1#
#4400
0#
#4410
b10 %
b100 (
b110 *
1#
#4420
0#
#4430
b11 %
b1000 (
b110 *
1#
#4440
0#
#4450
b1 %
b10000 (
b110 *
1#
#4460
0#
#4470
b0 %
b100000 (
b110 *
1#
#4480
0#
#4490
bx %
b111110000 &
1$
b1000000 (
b110 *
1#
#4500
0#
#4510
b0 %
0$
b100000000000000000 )
b1 (
b110 *
1#
#4520
0#
#4530
b10 (
b110 *
1#
#4540
0#
#4550
b11 %
b100 (
b110 *
1#
#4560
0#
#4570
b1000 (
b110 *
1#
#4580
0#
#4590
b1 %
b10000 (
b110 *
1#
#4600
0#
#4610
b0 %
b100000 (
b110 *
1#
#4620
0#
#4630
bx %
b1000000000 &
1$
b1000000 (
b110 *
1#
#4640
0#
#4650
b0 %
0$
b1 (
b100001000000000000 )
b110 *
1#
#4660
0#
#4670
b10 (
b110 *
1#
#4680
0#
#4690
b100 (
b110 *
1#
#4700
0#
#4710
b1000 (
b110 *
1#
#4720
0#
#4730
b10 %
b10000 (
b110 *
1#
#4740
0#
#4750
b0 %
b100000 (
b110 *
1#
#4760
0#
#4770
bx %
b1000010000 &
1$
b1000000 (
b110 *
1#
#4780
0#
#4790
b0 %
0$
b100010000000000000 )
b1 (
b110 *
1#
#4800
0#
#4810
b10 (
b110 *
1#
#4820
0#
#4830
b1 %
b100 (
b110 *
1#
#4840
0#
#4850
b0 %
b1000 (
b110 *
1#
#4860
0#
#4870
b10 %
b10000 (
b110 *
1#
#4880
0#
#4890
b0 %
b100000 (
b110 *
1#
#4900
0#
#4910
bx %
b1000100000 &
1$
b1000000 (
b110 *
1#
#4920
0#
#4930
b0 %
0$
b1 (
b100011000000000000 )
b110 *
1#
#4940
0#
#4950
b10 (
b110 *
1#
#4960
0#
#4970
b10 %
b100 (
b110 *
1#
#4980
0#
#4990
b0 %
b1000 (
b110 *
1#
#5000
0#
#5010
b10 %
b10000 (
b110 *
1#
#5020
0#
#5030
b0 %
b100000 (
b110 *
1#
#5040
0#
#5050
bx %
b1000110000 &
1$
b1000000 (
b110 *
1#
#5060
0#
#5070
b0 %
0$
b100100000000000000 )
b1 (
b110 *
1#
#5080
0#
#5090
b10 (
b110 *
1#
#5100
0#
#5110
b11 %
b100 (
b110 *
1#
#5120
0#
#5130
b0 %
b1000 (
b110 *
1#
#5140
0#
#5150
b10 %
b10000 (
b110 *
1#
#5160
0#
#5170
b0 %
b100000 (
b110 *
1#
#5180
0#
#5190
bx %
b1001000000 &
1$
b1000000 (
b110 *
1#
#5200
0#
#5210
b0 %
0$
b1 (
b100101000000000000 )
b110 *
1#
#5220
0#
#5230
b10 (
b110 *
1#
#5240
0#
#5250
b100 (
b110 *
1#
#5260
0#
#5270
b1 %
b1000 (
b110 *
1#
#5280
0#
#5290
b10 %
b10000 (
b110 *
1#
#5300
0#
#5310
b0 %
b100000 (
b110 *
1#
#5320
0#
#5330
bx %
b1001010000 &
1$
b1000000 (
b110 *
1#
#5340
0#
#5350
b0 %
0$
b100110000000000000 )
b1 (
b110 *
1#
#5360
0#
#5370
b10 (
b110 *
1#
#5380
0#
#5390
b1 %
b100 (
b110 *
1#
#5400
0#
#5410
b1000 (
b110 *
1#
#5420
0#
#5430
b10 %
b10000 (
b110 *
1#
#5440
0#
#5450
b0 %
b100000 (
b110 *
1#
#5460
0#
#5470
bx %
b1001100000 &
1$
b1000000 (
b110 *
1#
#5480
0#
#5490
b0 %
0$
b1 (
b100111000000000000 )
b110 *
1#
#5500
0#
#5510
b10 (
b110 *
1#
#5520
0#
#5530
b10 %
b100 (
b110 *
1#
#5540
0#
#5550
b1 %
b1000 (
b110 *
1#
#5560
0#
#5570
b10 %
b10000 (
b110 *
1#
#5580
0#
#5590
b0 %
b100000 (
b110 *
1#
#5600
0#
#5610
bx %
b1001110000 &
1$
b1000000 (
b110 *
1#
#5620
0#
#5630
b0 %
0$
b101000000000000000 )
b1 (
b110 *
1#
#5640
0#
#5650
b10 (
b110 *
1#
#5660
0#
#5670
b11 %
b100 (
b110 *
1#
#5680
0#
#5690
b1 %
b1000 (
b110 *
1#
#5700
0#
#5710
b10 %
b10000 (
b110 *
1#
#5720
0#
#5730
b0 %
b100000 (
b110 *
1#
#5740
0#
#5750
bx %
b1010000000 &
1$
b1000000 (
b110 *
1#
#5760
0#
#5770
b0 %
0$
b1 (
b101001000000000000 )
b110 *
1#
#5780
0#
#5790
b10 (
b110 *
1#
#5800
0#
#5810
b100 (
b110 *
1#
#5820
0#
#5830
b10 %
b1000 (
b110 *
1#
#5840
0#
#5850
b10000 (
b110 *
1#
#5860
0#
#5870
b0 %
b100000 (
b110 *
1#
#5880
0#
#5890
bx %
b1010010000 &
1$
b1000000 (
b110 *
1#
#5900
0#
#5910
b0 %
0$
b101010000000000000 )
b1 (
b110 *
1#
#5920
0#
#5930
b10 (
b110 *
1#
#5940
0#
#5950
b1 %
b100 (
b110 *
1#
#5960
0#
#5970
b10 %
b1000 (
b110 *
1#
#5980
0#
#5990
b10000 (
b110 *
1#
#6000
0#
#6010
b0 %
b100000 (
b110 *
1#
#6020
0#
#6030
bx %
b1010100000 &
1$
b1000000 (
b110 *
1#
#6040
0#
#6050
b0 %
0$
b1 (
b101011000000000000 )
b110 *
1#
#6060
0#
#6070
b10 (
b110 *
1#
#6080
0#
#6090
b10 %
b100 (
b110 *
1#
#6100
0#
#6110
b1000 (
b110 *
1#
#6120
0#
#6130
b10000 (
b110 *
1#
#6140
0#
#6150
b0 %
b100000 (
b110 *
1#
#6160
0#
#6170
bx %
b1010110000 &
1$
b1000000 (
b110 *
1#
#6180
0#
#6190
b0 %
0$
b101100000000000000 )
b1 (
b110 *
1#
#6200
0#
#6210
b10 (
b110 *
1#
#6220
0#
#6230
b11 %
b100 (
b110 *
1#
#6240
0#
#6250
b10 %
b1000 (
b110 *
1#
#6260
0#
#6270
b10000 (
b110 *
1#
#6280
0#
#6290
b0 %
b100000 (
b110 *
1#
#6300
0#
#6310
bx %
b1011000000 &
1$
b1000000 (
b110 *
1#
#6320
0#
#6330
b0 %
0$
b1 (
b101101000000000000 )
b110 *
1#
#6340
0#
#6350
b10 (
b110 *
1#
#6360
0#
#6370
b100 (
b110 *
1#
#6380
0#
#6390
b11 %
b1000 (
b110 *
1#
#6400
0#
#6410
b10 %
b10000 (
b110 *
1#
#6420
0#
#6430
b0 %
b100000 (
b110 *
1#
#6440
0#
#6450
bx %
b1011010000 &
1$
b1000000 (
b110 *
1#
#6460
0#
#6470
b0 %
0$
b101110000000000000 )
b1 (
b110 *
1#
#6480
0#
#6490
b10 (
b110 *
1#
#6500
0#
#6510
b1 %
b100 (
b110 *
1#
#6520
0#
#6530
b11 %
b1000 (
b110 *
1#
#6540
0#
#6550
b10 %
b10000 (
b110 *
1#
#6560
0#
#6570
b0 %
b100000 (
b110 *
1#
#6580
0#
#6590
bx %
b1011100000 &
1$
b1000000 (
b110 *
1#
#6600
0#
#6610
b0 %
0$
b1 (
b101111000000000000 )
b110 *
1#
#6620
0#
#6630
b10 (
b110 *
1#
#6640
0#
#6650
b10 %
b100 (
b110 *
1#
#6660
0#
#6670
b11 %
b1000 (
b110 *
1#
#6680
0#
#6690
b10 %
b10000 (
b110 *
1#
#6700
0#
#6710
b0 %
b100000 (
b110 *
1#
#6720
0#
#6730
bx %
b1011110000 &
1$
b1000000 (
b110 *
1#
#6740
0#
#6750
b0 %
0$
b110000000000000000 )
b1 (
b110 *
1#
#6760
0#
#6770
b10 (
b110 *
1#
#6780
0#
#6790
b11 %
b100 (
b110 *
1#
#6800
0#
#6810
b1000 (
b110 *
1#
#6820
0#
#6830
b10 %
b10000 (
b110 *
1#
#6840
0#
#6850
b0 %
b100000 (
b110 *
1#
#6860
0#
#6870
bx %
b1100000000 &
1$
b1000000 (
b110 *
1#
#6880
0#
#6890
b0 %
0$
b1 (
b110001000000000000 )
b110 *
1#
#6900
0#
#6910
b10 (
b110 *
1#
#6920
0#
#6930
b100 (
b110 *
1#
#6940
0#
#6950
b1000 (
b110 *
1#
#6960
0#
#6970
b11 %
b10000 (
b110 *
1#
#6980
0#
#6990
b0 %
b100000 (
b110 *
1#
#7000
0#
#7010
bx %
b1100010000 &
1$
b1000000 (
b110 *
1#
#7020
0#
#7030
b0 %
0$
b110010000000000000 )
b1 (
b110 *
1#
#7040
0#
#7050
b10 (
b110 *
1#
#7060
0#
#7070
b1 %
b100 (
b110 *
1#
#7080
0#
#7090
b0 %
b1000 (
b110 *
1#
#7100
0#
#7110
b11 %
b10000 (
b110 *
1#
#7120
0#
#7130
b0 %
b100000 (
b110 *
1#
#7140
0#
#7150
bx %
b1100100000 &
1$
b1000000 (
b110 *
1#
#7160
0#
#7170
b0 %
0$
b1 (
b110011000000000000 )
b110 *
1#
#7180
0#
#7190
b10 (
b110 *
1#
#7200
0#
#7210
b10 %
b100 (
b110 *
1#
#7220
0#
#7230
b0 %
b1000 (
b110 *
1#
#7240
0#
#7250
b11 %
b10000 (
b110 *
1#
#7260
0#
#7270
b0 %
b100000 (
b110 *
1#
#7280
0#
#7290
bx %
b1100110000 &
1$
b1000000 (
b110 *
1#
#7300
0#
#7310
b0 %
0$
b110100000000000000 )
b1 (
b110 *
1#
#7320
0#
#7330
b10 (
b110 *
1#
#7340
0#
#7350
b11 %
b100 (
b110 *
1#
#7360
0#
#7370
b0 %
b1000 (
b110 *
1#
#7380
0#
#7390
b11 %
b10000 (
b110 *
1#
#7400
0#
#7410
b0 %
b100000 (
b110 *
1#
#7420
0#
#7430
bx %
b1101000000 &
1$
b1000000 (
b110 *
1#
#7440
0#
#7450
b0 %
0$
b1 (
b110101000000000000 )
b110 *
1#
#7460
0#
#7470
b10 (
b110 *
1#
#7480
0#
#7490
b100 (
b110 *
1#
#7500
0#
#7510
b1 %
b1000 (
b110 *
1#
#7520
0#
#7530
b11 %
b10000 (
b110 *
1#
#7540
0#
#7550
b0 %
b100000 (
b110 *
1#
#7560
0#
#7570
bx %
b1101010000 &
1$
b1000000 (
b110 *
1#
#7580
0#
#7590
b0 %
0$
b110110000000000000 )
b1 (
b110 *
1#
#7600
0#
#7610
b10 (
b110 *
1#
#7620
0#
#7630
b1 %
b100 (
b110 *
1#
#7640
0#
#7650
b1000 (
b110 *
1#
#7660
0#
#7670
b11 %
b10000 (
b110 *
1#
#7680
0#
#7690
b0 %
b100000 (
b110 *
1#
#7700
0#
#7710
bx %
b1101100000 &
1$
b1000000 (
b110 *
1#
#7720
0#
#7730
b0 %
0$
b1 (
b110111000000000000 )
b110 *
1#
#7740
0#
#7750
b10 (
b110 *
1#
#7760
0#
#7770
b10 %
b100 (
b110 *
1#
#7780
0#
#7790
b1 %
b1000 (
b110 *
1#
#7800
0#
#7810
b11 %
b10000 (
b110 *
1#
#7820
0#
#7830
b0 %
b100000 (
b110 *
1#
#7840
0#
#7850
bx %
b1101110000 &
1$
b1000000 (
b110 *
1#
#7860
0#
#7870
b0 %
0$
b111000000000000000 )
b1 (
b110 *
1#
#7880
0#
#7890
b10 (
b110 *
1#
#7900
0#
#7910
b11 %
b100 (
b110 *
1#
#7920
0#
#7930
b1 %
b1000 (
b110 *
1#
#7940
0#
#7950
b11 %
b10000 (
b110 *
1#
#7960
0#
#7970
b0 %
b100000 (
b110 *
1#
#7980
0#
#7990
bx %
b1110000000 &
1$
b1000000 (
b110 *
1#
#8000
0#
#8010
b0 %
0$
b1 (
b111001000000000000 )
b110 *
1#
#8020
0#
#8030
b10 (
b110 *
1#
#8040
0#
#8050
b100 (
b110 *
1#
#8060
0#
#8070
b10 %
b1000 (
b110 *
1#
#8080
0#
#8090
b11 %
b10000 (
b110 *
1#
#8100
0#
#8110
b0 %
b100000 (
b110 *
1#
#8120
0#
#8130
bx %
b1110010000 &
1$
b1000000 (
b110 *
1#
#8140
0#
#8150
b0 %
0$
b111010000000000000 )
b1 (
b110 *
1#
#8160
0#
#8170
b10 (
b110 *
1#
#8180
0#
#8190
b1 %
b100 (
b110 *
1#
#8200
0#
#8210
b10 %
b1000 (
b110 *
1#
#8220
0#
#8230
b11 %
b10000 (
b110 *
1#
#8240
0#
#8250
b0 %
b100000 (
b110 *
1#
#8260
0#
#8270
bx %
b1110100000 &
1$
b1000000 (
b110 *
1#
#8280
0#
#8290
b0 %
0$
b1 (
b111011000000000000 )
b110 *
1#
#8300
0#
#8310
b10 (
b110 *
1#
#8320
0#
#8330
b10 %
b100 (
b110 *
1#
#8340
0#
#8350
b1000 (
b110 *
1#
#8360
0#
#8370
b11 %
b10000 (
b110 *
1#
#8380
0#
#8390
b0 %
b100000 (
b110 *
1#
#8400
0#
